<?xml version="1.0" encoding="utf-8"?>
<TablePopulationObject xmlns:xsi="http://www.w3.org/2001/XMLSchema-instance" xmlns:xsd="http://www.w3.org/2001/XMLSchema">
  <ID>query_YP_PRODUCT_FAB</ID>
  <PopulationObjectName>query_YP_PRODUCT_FAB</PopulationObjectName>
  <TableName>YP_PRODUCT_FAB</TableName>
  <RootItemID>query_query_YP_PRODUCT_FAB</RootItemID>
  <LazyDataUpdate syncMethod="Inherited" performEvery="1.00:00:00">
    <TruncateBeforeSync>false</TruncateBeforeSync>
  </LazyDataUpdate>
  <SimpleObject>true</SimpleObject>
  <InputArguments>
    <Arg name="CUSTOMER_ID" id="queryCol_0" dataType="Integer" index="0" />
    <Arg name="PRODUCT_CODE" id="queryCol_1" dataType="Text" index="1" />
    <Arg name="PRODUCT_ISSUE_NUM" id="queryCol_2" dataType="Integer" index="2" />
    <Arg name="PRODUCT_STATUS" id="queryCol_3" dataType="Integer" index="3" />
    <Arg name="RETIREMENT_STATUS" id="queryCol_4" dataType="Text" index="4" />
    <Arg name="ACTIVITY_TYPE" id="queryCol_5" dataType="Integer" index="5" />
    <Arg name="ADDITIONAL_ACTIVITY" id="queryCol_6" dataType="Integer" index="6" />
    <Arg name="ACTIVITY_DATE" id="queryCol_7" dataType="Text" index="7" />
    <Arg name="ACTIVITY_UPDATE_DATE" id="queryCol_8" dataType="Text" index="8" />
    <Arg name="ADVANCE_SALE_IND" id="queryCol_9" dataType="Text" index="9" />
    <Arg name="PROSPECT_CODE" id="queryCol_10" dataType="Integer" index="10" />
    <Arg name="PROD_CURR_PROS_CODE" id="queryCol_11" dataType="Integer" index="11" />
    <Arg name="PROSPECT_AGE" id="queryCol_12" dataType="Integer" index="12" />
    <Arg name="DOMINANT_HEADING" id="queryCol_13" dataType="Integer" index="13" />
    <Arg name="DOMINANT_HEADING_AMT" id="queryCol_14" dataType="Real" index="14" />
    <Arg name="LAST_CONT_PRINT_DATE" id="queryCol_15" dataType="Text" index="15" />
    <Arg name="COMPLAINT_IND" id="queryCol_16" dataType="Text" index="16" />
    <Arg name="COMPLAINT_DATE" id="queryCol_17" dataType="Text" index="17" />
    <Arg name="DIVISION_ARRIVE_DATE" id="queryCol_18" dataType="Text" index="18" />
    <Arg name="COMMERCIAL_NAME" id="queryCol_19" dataType="Text" index="19" />
    <Arg name="SRCH_COMMERCIAL_NAME" id="queryCol_20" dataType="Text" index="20" />
    <Arg name="DISPLAY_AD_EXIST_IND" id="queryCol_21" dataType="Text" index="21" />
    <Arg name="LOCAL_FOREIGN_IND" id="queryCol_22" dataType="Text" index="22" />
    <Arg name="CANVASS_CODE" id="queryCol_23" dataType="Text" index="23" />
    <Arg name="CANVASS_ISSUE_NUM" id="queryCol_24" dataType="Integer" index="24" />
    <Arg name="FIRST_ASSIGN_ID" id="queryCol_25" dataType="Integer" index="25" />
    <Arg name="FIRST_ASSIGN_DATE" id="queryCol_26" dataType="Text" index="26" />
    <Arg name="CURRENT_ASSIGN_ID" id="queryCol_27" dataType="Integer" index="27" />
    <Arg name="CURRENT_ASSIGN_DATE" id="queryCol_28" dataType="Text" index="28" />
    <Arg name="CONTRACT_LOAD_PHASE" id="queryCol_29" dataType="Integer" index="29" />
    <Arg name="CONTINUITY_AGE" id="queryCol_30" dataType="Integer" index="30" />
    <Arg name="CHANNEL_AGE" id="queryCol_31" dataType="Integer" index="31" />
    <Arg name="ASSIST_ASSIGN_ID" id="queryCol_32" dataType="Integer" index="32" />
    <Arg name="ASSIST_PERCENTAGE" id="queryCol_33" dataType="Real" index="33" />
    <Arg name="LENDING_ASSIGN_ID" id="queryCol_34" dataType="Integer" index="34" />
    <Arg name="SELL_CANVASS_CODE" id="queryCol_35" dataType="Text" index="35" />
    <Arg name="SELL_CANV_ISS_NUM" id="queryCol_36" dataType="Integer" index="36" />
    <Arg name="SELL_ASSIGN_ID" id="queryCol_37" dataType="Integer" index="37" />
    <Arg name="CMSN_CANVASS_CODE" id="queryCol_38" dataType="Text" index="38" />
    <Arg name="CMSN_CANV_ISS_NUM" id="queryCol_39" dataType="Integer" index="39" />
    <Arg name="CMSN_ASSIGN_ID" id="queryCol_40" dataType="Integer" index="40" />
    <Arg name="QUERY_STATUS" id="queryCol_41" dataType="Integer" index="41" />
    <Arg name="COMPLAINT_ASGN_ID" id="queryCol_42" dataType="Integer" index="42" />
    <Arg name="NIR_PRODUCT_IND" id="queryCol_43" dataType="Text" index="43" />
    <Arg name="START_PUBLISH_DATE" id="queryCol_44" dataType="Text" index="44" />
    <Arg name="DURATION" id="queryCol_45" dataType="Integer" index="45" />
    <Arg name="ACTUAL_END_PUB_DATE" id="queryCol_46" dataType="Text" index="46" />
    <Arg name="RENEWAL_CONTRACT_IND" id="queryCol_47" dataType="Text" index="47" />
    <Arg name="PRODUCT_NAME" id="queryCol_48" dataType="Text" index="48" />
    <Arg name="NUM_OF_BOTS_ITEMS" id="queryCol_49" dataType="Integer" index="49" />
    <Arg name="NUM_OF_NISD_ITEMS" id="queryCol_50" dataType="Integer" index="50" />
    <Arg name="NUM_QUERIED_ITEMS" id="queryCol_51" dataType="Integer" index="51" />
    <Arg name="LAST_YEAR_NISD_AMT" id="queryCol_52" dataType="Real" index="52" />
    <Arg name="ORIG_ASGN_BOTS_AMT" id="queryCol_53" dataType="Real" index="53" />
    <Arg name="OVER_RATE_BOTS_AMT" id="queryCol_54" dataType="Real" index="54" />
    <Arg name="BOTS_AMOUNT" id="queryCol_55" dataType="Real" index="55" />
    <Arg name="NISD_AMOUNT" id="queryCol_56" dataType="Real" index="56" />
    <Arg name="RESULTS_NISD_AMT" id="queryCol_57" dataType="Real" index="57" />
    <Arg name="TAX_ID_LETTER" id="queryCol_58" dataType="Text" index="58" />
    <Arg name="TAX_ID_DATE" id="queryCol_59" dataType="Text" index="59" />
    <Arg name="TAX_ID_CODE" id="queryCol_60" dataType="Text" index="60" />
    <Arg name="E_MAIL_ADDRESS" id="queryCol_61" dataType="Text" index="61" />
    <Arg name="ASSIST_CANVASS_CODE" id="queryCol_62" dataType="Text" index="62" />
    <Arg name="ASSIST_CANV_ISS_NUM" id="queryCol_63" dataType="Integer" index="63" />
    <Arg name="CURP_ID" id="queryCol_64" dataType="Text" index="64" />
    <Arg name="HIGH_WGHT_COLOR_CODE" id="queryCol_65" dataType="Text" index="65" />
    <Arg name="PREV_HIGH_WGHT_COLOR" id="queryCol_66" dataType="Text" index="66" />
    <Arg name="CTCR_BATCH_PROG_ID" id="queryCol_67" dataType="Text" index="67" />
    <Arg name="CTCR_BATCH_PROG_DT" id="queryCol_68" dataType="Text" index="68" />
    <Arg name="CTCR_ONLINE_USER_ID" id="queryCol_69" dataType="Integer" index="69" />
    <Arg name="CTCR_ONLINE_PROG_ID" id="queryCol_70" dataType="Text" index="70" />
    <Arg name="CTCR_ONLINE_PROG_DT" id="queryCol_71" dataType="Text" index="71" />
    <Arg name="CTCR_SYS_CRE_DT" id="queryCol_72" dataType="Text" index="72" />
    <Arg name="CTCR_SYS_UPD_DT" id="queryCol_73" dataType="Text" index="73" />
    <Arg name="CTCR_DBI_PROG_ID" id="queryCol_74" dataType="Text" index="74" />
    <Arg name="CTCR_DBI_PROG_DT" id="queryCol_75" dataType="Text" index="75" />
    <Arg name="CTCR_CNV_DT" id="queryCol_76" dataType="Text" index="76" />
    <Arg name="CTCR_EVENT_ID" id="queryCol_77" dataType="Integer" index="77" />
    <Arg name="SUBSC_UP_TO_DATE_AMT" id="queryCol_78" dataType="Real" index="78" />
    <Arg name="NIR_CANCEL_DATE" id="queryCol_79" dataType="Text" index="79" />
    <Arg name="PRD_FORCED_REP_ID" id="queryCol_80" dataType="Integer" index="80" />
    <Arg name="PRD_FORCED_CHANNEL_CODE" id="queryCol_81" dataType="Text" index="81" />
    <Arg name="PRD_FORCE_TYPE" id="queryCol_82" dataType="Integer" index="82" />
    <Arg name="SIG_NAME" id="queryCol_83" dataType="Text" index="83" />
    <Arg name="SIG_DATE_PREV" id="queryCol_84" dataType="Text" index="84" />
    <Arg name="PREP_STATUS" id="queryCol_85" dataType="Text" index="85" />
    <Arg name="DISCOUNT_AMT" id="queryCol_86" dataType="Real" index="86" />
    <Arg name="DISCOUNT_BOTS_AMT" id="queryCol_87" dataType="Real" index="87" />
    <Arg name="ORIG_RETIREMENT_STATUS" id="queryCol_88" dataType="Text" index="88" />
    <Arg name="UDAC_CMSN_POINTS" id="queryCol_89" dataType="Real" index="89" />
    <Arg name="PREV_UDAC_CMSN_POINTS" id="queryCol_90" dataType="Real" index="90" />
    <Arg name="NIR_PROD_RELATED" id="queryCol_91" dataType="Text" index="91" />
    <Arg name="MIX_PRODUCT_IND" id="queryCol_92" dataType="Text" index="92" />
    <Arg name="PP_SELECTED_DATE" id="queryCol_93" dataType="Text" index="93" />
    <Arg name="MEDIA_AGENT_IND" id="queryCol_94" dataType="Text" index="94" />
    <Arg name="MEDIA_AGENT_CODE" id="queryCol_95" dataType="Text" index="95" />
    <Arg name="PYME_IND" id="queryCol_96" dataType="Text" index="96" />
    <Arg name="CONVERSION_IND" id="queryCol_97" dataType="Text" index="97" />
  </InputArguments>
  <ItemsList>
    <Item xsi:type="DBQueryDataSave" id="query_query_YP_PRODUCT_FAB" name="query_YP_PRODUCT_FAB" nodeOrder="0" module="DBQuery" mapObjectModule="DBQuery" connName="ORA_TEST">
      <OutputsList>
        <Output xsi:type="DBQueryDataSaveColumn" id="queryCol_0" name="CUSTOMER_ID" dataType="Integer" index="0" />
        <Output xsi:type="DBQueryDataSaveColumn" id="queryCol_1" name="PRODUCT_CODE" dataType="Text" index="1" />
        <Output xsi:type="DBQueryDataSaveColumn" id="queryCol_2" name="PRODUCT_ISSUE_NUM" dataType="Integer" index="2" />
        <Output xsi:type="DBQueryDataSaveColumn" id="queryCol_3" name="PRODUCT_STATUS" dataType="Integer" index="3" />
        <Output xsi:type="DBQueryDataSaveColumn" id="queryCol_4" name="RETIREMENT_STATUS" dataType="Text" index="4" />
        <Output xsi:type="DBQueryDataSaveColumn" id="queryCol_5" name="ACTIVITY_TYPE" dataType="Integer" index="5" />
        <Output xsi:type="DBQueryDataSaveColumn" id="queryCol_6" name="ADDITIONAL_ACTIVITY" dataType="Integer" index="6" />
        <Output xsi:type="DBQueryDataSaveColumn" id="queryCol_7" name="ACTIVITY_DATE" dataType="Text" index="7" />
        <Output xsi:type="DBQueryDataSaveColumn" id="queryCol_8" name="ACTIVITY_UPDATE_DATE" dataType="Text" index="8" />
        <Output xsi:type="DBQueryDataSaveColumn" id="queryCol_9" name="ADVANCE_SALE_IND" dataType="Text" index="9" />
        <Output xsi:type="DBQueryDataSaveColumn" id="queryCol_10" name="PROSPECT_CODE" dataType="Integer" index="10" />
        <Output xsi:type="DBQueryDataSaveColumn" id="queryCol_11" name="PROD_CURR_PROS_CODE" dataType="Integer" index="11" />
        <Output xsi:type="DBQueryDataSaveColumn" id="queryCol_12" name="PROSPECT_AGE" dataType="Integer" index="12" />
        <Output xsi:type="DBQueryDataSaveColumn" id="queryCol_13" name="DOMINANT_HEADING" dataType="Integer" index="13" />
        <Output xsi:type="DBQueryDataSaveColumn" id="queryCol_14" name="DOMINANT_HEADING_AMT" dataType="Real" index="14" />
        <Output xsi:type="DBQueryDataSaveColumn" id="queryCol_15" name="LAST_CONT_PRINT_DATE" dataType="Text" index="15" />
        <Output xsi:type="DBQueryDataSaveColumn" id="queryCol_16" name="COMPLAINT_IND" dataType="Text" index="16" />
        <Output xsi:type="DBQueryDataSaveColumn" id="queryCol_17" name="COMPLAINT_DATE" dataType="Text" index="17" />
        <Output xsi:type="DBQueryDataSaveColumn" id="queryCol_18" name="DIVISION_ARRIVE_DATE" dataType="Text" index="18" />
        <Output xsi:type="DBQueryDataSaveColumn" id="queryCol_19" name="COMMERCIAL_NAME" dataType="Text" index="19" />
        <Output xsi:type="DBQueryDataSaveColumn" id="queryCol_20" name="SRCH_COMMERCIAL_NAME" dataType="Text" index="20" />
        <Output xsi:type="DBQueryDataSaveColumn" id="queryCol_21" name="DISPLAY_AD_EXIST_IND" dataType="Text" index="21" />
        <Output xsi:type="DBQueryDataSaveColumn" id="queryCol_22" name="LOCAL_FOREIGN_IND" dataType="Text" index="22" />
        <Output xsi:type="DBQueryDataSaveColumn" id="queryCol_23" name="CANVASS_CODE" dataType="Text" index="23" />
        <Output xsi:type="DBQueryDataSaveColumn" id="queryCol_24" name="CANVASS_ISSUE_NUM" dataType="Integer" index="24" />
        <Output xsi:type="DBQueryDataSaveColumn" id="queryCol_25" name="FIRST_ASSIGN_ID" dataType="Integer" index="25" />
        <Output xsi:type="DBQueryDataSaveColumn" id="queryCol_26" name="FIRST_ASSIGN_DATE" dataType="Text" index="26" />
        <Output xsi:type="DBQueryDataSaveColumn" id="queryCol_27" name="CURRENT_ASSIGN_ID" dataType="Integer" index="27" />
        <Output xsi:type="DBQueryDataSaveColumn" id="queryCol_28" name="CURRENT_ASSIGN_DATE" dataType="Text" index="28" />
        <Output xsi:type="DBQueryDataSaveColumn" id="queryCol_29" name="CONTRACT_LOAD_PHASE" dataType="Integer" index="29" />
        <Output xsi:type="DBQueryDataSaveColumn" id="queryCol_30" name="CONTINUITY_AGE" dataType="Integer" index="30" />
        <Output xsi:type="DBQueryDataSaveColumn" id="queryCol_31" name="CHANNEL_AGE" dataType="Integer" index="31" />
        <Output xsi:type="DBQueryDataSaveColumn" id="queryCol_32" name="ASSIST_ASSIGN_ID" dataType="Integer" index="32" />
        <Output xsi:type="DBQueryDataSaveColumn" id="queryCol_33" name="ASSIST_PERCENTAGE" dataType="Real" index="33" />
        <Output xsi:type="DBQueryDataSaveColumn" id="queryCol_34" name="LENDING_ASSIGN_ID" dataType="Integer" index="34" />
        <Output xsi:type="DBQueryDataSaveColumn" id="queryCol_35" name="SELL_CANVASS_CODE" dataType="Text" index="35" />
        <Output xsi:type="DBQueryDataSaveColumn" id="queryCol_36" name="SELL_CANV_ISS_NUM" dataType="Integer" index="36" />
        <Output xsi:type="DBQueryDataSaveColumn" id="queryCol_37" name="SELL_ASSIGN_ID" dataType="Integer" index="37" />
        <Output xsi:type="DBQueryDataSaveColumn" id="queryCol_38" name="CMSN_CANVASS_CODE" dataType="Text" index="38" />
        <Output xsi:type="DBQueryDataSaveColumn" id="queryCol_39" name="CMSN_CANV_ISS_NUM" dataType="Integer" index="39" />
        <Output xsi:type="DBQueryDataSaveColumn" id="queryCol_40" name="CMSN_ASSIGN_ID" dataType="Integer" index="40" />
        <Output xsi:type="DBQueryDataSaveColumn" id="queryCol_41" name="QUERY_STATUS" dataType="Integer" index="41" />
        <Output xsi:type="DBQueryDataSaveColumn" id="queryCol_42" name="COMPLAINT_ASGN_ID" dataType="Integer" index="42" />
        <Output xsi:type="DBQueryDataSaveColumn" id="queryCol_43" name="NIR_PRODUCT_IND" dataType="Text" index="43" />
        <Output xsi:type="DBQueryDataSaveColumn" id="queryCol_44" name="START_PUBLISH_DATE" dataType="Text" index="44" />
        <Output xsi:type="DBQueryDataSaveColumn" id="queryCol_45" name="DURATION" dataType="Integer" index="45" />
        <Output xsi:type="DBQueryDataSaveColumn" id="queryCol_46" name="ACTUAL_END_PUB_DATE" dataType="Text" index="46" />
        <Output xsi:type="DBQueryDataSaveColumn" id="queryCol_47" name="RENEWAL_CONTRACT_IND" dataType="Text" index="47" />
        <Output xsi:type="DBQueryDataSaveColumn" id="queryCol_48" name="PRODUCT_NAME" dataType="Text" index="48" />
        <Output xsi:type="DBQueryDataSaveColumn" id="queryCol_49" name="NUM_OF_BOTS_ITEMS" dataType="Integer" index="49" />
        <Output xsi:type="DBQueryDataSaveColumn" id="queryCol_50" name="NUM_OF_NISD_ITEMS" dataType="Integer" index="50" />
        <Output xsi:type="DBQueryDataSaveColumn" id="queryCol_51" name="NUM_QUERIED_ITEMS" dataType="Integer" index="51" />
        <Output xsi:type="DBQueryDataSaveColumn" id="queryCol_52" name="LAST_YEAR_NISD_AMT" dataType="Real" index="52" />
        <Output xsi:type="DBQueryDataSaveColumn" id="queryCol_53" name="ORIG_ASGN_BOTS_AMT" dataType="Real" index="53" />
        <Output xsi:type="DBQueryDataSaveColumn" id="queryCol_54" name="OVER_RATE_BOTS_AMT" dataType="Real" index="54" />
        <Output xsi:type="DBQueryDataSaveColumn" id="queryCol_55" name="BOTS_AMOUNT" dataType="Real" index="55" />
        <Output xsi:type="DBQueryDataSaveColumn" id="queryCol_56" name="NISD_AMOUNT" dataType="Real" index="56" />
        <Output xsi:type="DBQueryDataSaveColumn" id="queryCol_57" name="RESULTS_NISD_AMT" dataType="Real" index="57" />
        <Output xsi:type="DBQueryDataSaveColumn" id="queryCol_58" name="TAX_ID_LETTER" dataType="Text" index="58" />
        <Output xsi:type="DBQueryDataSaveColumn" id="queryCol_59" name="TAX_ID_DATE" dataType="Text" index="59" />
        <Output xsi:type="DBQueryDataSaveColumn" id="queryCol_60" name="TAX_ID_CODE" dataType="Text" index="60" />
        <Output xsi:type="DBQueryDataSaveColumn" id="queryCol_61" name="E_MAIL_ADDRESS" dataType="Text" index="61" />
        <Output xsi:type="DBQueryDataSaveColumn" id="queryCol_62" name="ASSIST_CANVASS_CODE" dataType="Text" index="62" />
        <Output xsi:type="DBQueryDataSaveColumn" id="queryCol_63" name="ASSIST_CANV_ISS_NUM" dataType="Integer" index="63" />
        <Output xsi:type="DBQueryDataSaveColumn" id="queryCol_64" name="CURP_ID" dataType="Text" index="64" />
        <Output xsi:type="DBQueryDataSaveColumn" id="queryCol_65" name="HIGH_WGHT_COLOR_CODE" dataType="Text" index="65" />
        <Output xsi:type="DBQueryDataSaveColumn" id="queryCol_66" name="PREV_HIGH_WGHT_COLOR" dataType="Text" index="66" />
        <Output xsi:type="DBQueryDataSaveColumn" id="queryCol_67" name="CTCR_BATCH_PROG_ID" dataType="Text" index="67" />
        <Output xsi:type="DBQueryDataSaveColumn" id="queryCol_68" name="CTCR_BATCH_PROG_DT" dataType="Text" index="68" />
        <Output xsi:type="DBQueryDataSaveColumn" id="queryCol_69" name="CTCR_ONLINE_USER_ID" dataType="Integer" index="69" />
        <Output xsi:type="DBQueryDataSaveColumn" id="queryCol_70" name="CTCR_ONLINE_PROG_ID" dataType="Text" index="70" />
        <Output xsi:type="DBQueryDataSaveColumn" id="queryCol_71" name="CTCR_ONLINE_PROG_DT" dataType="Text" index="71" />
        <Output xsi:type="DBQueryDataSaveColumn" id="queryCol_72" name="CTCR_SYS_CRE_DT" dataType="Text" index="72" />
        <Output xsi:type="DBQueryDataSaveColumn" id="queryCol_73" name="CTCR_SYS_UPD_DT" dataType="Text" index="73" />
        <Output xsi:type="DBQueryDataSaveColumn" id="queryCol_74" name="CTCR_DBI_PROG_ID" dataType="Text" index="74" />
        <Output xsi:type="DBQueryDataSaveColumn" id="queryCol_75" name="CTCR_DBI_PROG_DT" dataType="Text" index="75" />
        <Output xsi:type="DBQueryDataSaveColumn" id="queryCol_76" name="CTCR_CNV_DT" dataType="Text" index="76" />
        <Output xsi:type="DBQueryDataSaveColumn" id="queryCol_77" name="CTCR_EVENT_ID" dataType="Integer" index="77" />
        <Output xsi:type="DBQueryDataSaveColumn" id="queryCol_78" name="SUBSC_UP_TO_DATE_AMT" dataType="Real" index="78" />
        <Output xsi:type="DBQueryDataSaveColumn" id="queryCol_79" name="NIR_CANCEL_DATE" dataType="Text" index="79" />
        <Output xsi:type="DBQueryDataSaveColumn" id="queryCol_80" name="PRD_FORCED_REP_ID" dataType="Integer" index="80" />
        <Output xsi:type="DBQueryDataSaveColumn" id="queryCol_81" name="PRD_FORCED_CHANNEL_CODE" dataType="Text" index="81" />
        <Output xsi:type="DBQueryDataSaveColumn" id="queryCol_82" name="PRD_FORCE_TYPE" dataType="Integer" index="82" />
        <Output xsi:type="DBQueryDataSaveColumn" id="queryCol_83" name="SIG_NAME" dataType="Text" index="83" />
        <Output xsi:type="DBQueryDataSaveColumn" id="queryCol_84" name="SIG_DATE_PREV" dataType="Text" index="84" />
        <Output xsi:type="DBQueryDataSaveColumn" id="queryCol_85" name="PREP_STATUS" dataType="Text" index="85" />
        <Output xsi:type="DBQueryDataSaveColumn" id="queryCol_86" name="DISCOUNT_AMT" dataType="Real" index="86" />
        <Output xsi:type="DBQueryDataSaveColumn" id="queryCol_87" name="DISCOUNT_BOTS_AMT" dataType="Real" index="87" />
        <Output xsi:type="DBQueryDataSaveColumn" id="queryCol_88" name="ORIG_RETIREMENT_STATUS" dataType="Text" index="88" />
        <Output xsi:type="DBQueryDataSaveColumn" id="queryCol_89" name="UDAC_CMSN_POINTS" dataType="Real" index="89" />
        <Output xsi:type="DBQueryDataSaveColumn" id="queryCol_90" name="PREV_UDAC_CMSN_POINTS" dataType="Real" index="90" />
        <Output xsi:type="DBQueryDataSaveColumn" id="queryCol_91" name="NIR_PROD_RELATED" dataType="Text" index="91" />
        <Output xsi:type="DBQueryDataSaveColumn" id="queryCol_92" name="MIX_PRODUCT_IND" dataType="Text" index="92" />
        <Output xsi:type="DBQueryDataSaveColumn" id="queryCol_93" name="PP_SELECTED_DATE" dataType="Text" index="93" />
        <Output xsi:type="DBQueryDataSaveColumn" id="queryCol_94" name="MEDIA_AGENT_IND" dataType="Text" index="94" />
        <Output xsi:type="DBQueryDataSaveColumn" id="queryCol_95" name="MEDIA_AGENT_CODE" dataType="Text" index="95" />
        <Output xsi:type="DBQueryDataSaveColumn" id="queryCol_96" name="PYME_IND" dataType="Text" index="96" />
        <Output xsi:type="DBQueryDataSaveColumn" id="queryCol_97" name="CONVERSION_IND" dataType="Text" index="97" />
      </OutputsList>
      <SQL><![CDATA[SELECT * FROM YP_PRODUCT_FAB]]></SQL>
    </Item>
  </ItemsList>
  <LinksList>
    <Link partId="200" fromNodeOrder="0" fromItemID="query_query_YP_PRODUCT_FAB" fromColID="queryCol_0" toItemID="tbl_YP_PRODUCT_FAB" toColID="tblCol_e564896783cc4e8e825cd288176c3547" />
    <Link partId="201" fromNodeOrder="0" fromItemID="query_query_YP_PRODUCT_FAB" fromColID="queryCol_1" toItemID="tbl_YP_PRODUCT_FAB" toColID="tblCol_71bf8b372a8d4473bab63ddb863e5ad6" />
    <Link partId="202" fromNodeOrder="0" fromItemID="query_query_YP_PRODUCT_FAB" fromColID="queryCol_2" toItemID="tbl_YP_PRODUCT_FAB" toColID="tblCol_61cd5de7627245f6bb908ef3e65732d2" />
    <Link partId="203" fromNodeOrder="0" fromItemID="query_query_YP_PRODUCT_FAB" fromColID="queryCol_3" toItemID="tbl_YP_PRODUCT_FAB" toColID="tblCol_f73d199967034b5384496ff6ce88fea8" />
    <Link partId="204" fromNodeOrder="0" fromItemID="query_query_YP_PRODUCT_FAB" fromColID="queryCol_4" toItemID="tbl_YP_PRODUCT_FAB" toColID="tblCol_590c6999cef44c48bb8c9cdb2eb4b7d5" />
    <Link partId="205" fromNodeOrder="0" fromItemID="query_query_YP_PRODUCT_FAB" fromColID="queryCol_5" toItemID="tbl_YP_PRODUCT_FAB" toColID="tblCol_9d95c77254d04c399dc335aed5f7cba8" />
    <Link partId="206" fromNodeOrder="0" fromItemID="query_query_YP_PRODUCT_FAB" fromColID="queryCol_6" toItemID="tbl_YP_PRODUCT_FAB" toColID="tblCol_9b0bf615a0094867b88dedc4bbdd4c8f" />
    <Link partId="207" fromNodeOrder="0" fromItemID="query_query_YP_PRODUCT_FAB" fromColID="queryCol_7" toItemID="tbl_YP_PRODUCT_FAB" toColID="tblCol_4c83e738afed4f5cb68473d8231a6cda" />
    <Link partId="208" fromNodeOrder="0" fromItemID="query_query_YP_PRODUCT_FAB" fromColID="queryCol_8" toItemID="tbl_YP_PRODUCT_FAB" toColID="tblCol_d5d955999aa24c06ad51fba3bcc94a64" />
    <Link partId="209" fromNodeOrder="0" fromItemID="query_query_YP_PRODUCT_FAB" fromColID="queryCol_9" toItemID="tbl_YP_PRODUCT_FAB" toColID="tblCol_be019b98eeb04a9d921b2fa3fa2d8dce" />
    <Link partId="210" fromNodeOrder="0" fromItemID="query_query_YP_PRODUCT_FAB" fromColID="queryCol_10" toItemID="tbl_YP_PRODUCT_FAB" toColID="tblCol_21e83b7a5ebc40b4bff684be7a28459e" />
    <Link partId="211" fromNodeOrder="0" fromItemID="query_query_YP_PRODUCT_FAB" fromColID="queryCol_11" toItemID="tbl_YP_PRODUCT_FAB" toColID="tblCol_c7cd1b8661984a8a965f4caea68cab7f" />
    <Link partId="212" fromNodeOrder="0" fromItemID="query_query_YP_PRODUCT_FAB" fromColID="queryCol_12" toItemID="tbl_YP_PRODUCT_FAB" toColID="tblCol_d7c9f7f5ec4a4378a3794b3a4cba5592" />
    <Link partId="213" fromNodeOrder="0" fromItemID="query_query_YP_PRODUCT_FAB" fromColID="queryCol_13" toItemID="tbl_YP_PRODUCT_FAB" toColID="tblCol_35c2f99eb6dd4722a344983e258b1d20" />
    <Link partId="214" fromNodeOrder="0" fromItemID="query_query_YP_PRODUCT_FAB" fromColID="queryCol_14" toItemID="tbl_YP_PRODUCT_FAB" toColID="tblCol_eb548d6548c2421da190fd1c31d941af" />
    <Link partId="215" fromNodeOrder="0" fromItemID="query_query_YP_PRODUCT_FAB" fromColID="queryCol_15" toItemID="tbl_YP_PRODUCT_FAB" toColID="tblCol_1f0a81bcf17c4e03bf2c6835ec945dfc" />
    <Link partId="216" fromNodeOrder="0" fromItemID="query_query_YP_PRODUCT_FAB" fromColID="queryCol_16" toItemID="tbl_YP_PRODUCT_FAB" toColID="tblCol_6b5eb31ffd1743db912edb943a124f81" />
    <Link partId="217" fromNodeOrder="0" fromItemID="query_query_YP_PRODUCT_FAB" fromColID="queryCol_17" toItemID="tbl_YP_PRODUCT_FAB" toColID="tblCol_8f1ccbe14f254f70bd13ca955b007978" />
    <Link partId="218" fromNodeOrder="0" fromItemID="query_query_YP_PRODUCT_FAB" fromColID="queryCol_18" toItemID="tbl_YP_PRODUCT_FAB" toColID="tblCol_7801150033764d91a43819767355d1c7" />
    <Link partId="219" fromNodeOrder="0" fromItemID="query_query_YP_PRODUCT_FAB" fromColID="queryCol_19" toItemID="tbl_YP_PRODUCT_FAB" toColID="tblCol_62f6a3321fd945dabff36b9852351794" />
    <Link partId="220" fromNodeOrder="0" fromItemID="query_query_YP_PRODUCT_FAB" fromColID="queryCol_20" toItemID="tbl_YP_PRODUCT_FAB" toColID="tblCol_7d824b9b542d4754bb35fc17edfb05c4" />
    <Link partId="221" fromNodeOrder="0" fromItemID="query_query_YP_PRODUCT_FAB" fromColID="queryCol_21" toItemID="tbl_YP_PRODUCT_FAB" toColID="tblCol_3f83f978b50b499888e43a11ff77c68a" />
    <Link partId="222" fromNodeOrder="0" fromItemID="query_query_YP_PRODUCT_FAB" fromColID="queryCol_22" toItemID="tbl_YP_PRODUCT_FAB" toColID="tblCol_c9732f1ee2844207b5d9d789d1993980" />
    <Link partId="223" fromNodeOrder="0" fromItemID="query_query_YP_PRODUCT_FAB" fromColID="queryCol_23" toItemID="tbl_YP_PRODUCT_FAB" toColID="tblCol_a840ad70404c491b87c6df7bee2c4e69" />
    <Link partId="224" fromNodeOrder="0" fromItemID="query_query_YP_PRODUCT_FAB" fromColID="queryCol_24" toItemID="tbl_YP_PRODUCT_FAB" toColID="tblCol_aef55e12f58345f7a1e5c433f4483489" />
    <Link partId="225" fromNodeOrder="0" fromItemID="query_query_YP_PRODUCT_FAB" fromColID="queryCol_25" toItemID="tbl_YP_PRODUCT_FAB" toColID="tblCol_486b8d812ead49e6b2e86ffe0a48601a" />
    <Link partId="226" fromNodeOrder="0" fromItemID="query_query_YP_PRODUCT_FAB" fromColID="queryCol_26" toItemID="tbl_YP_PRODUCT_FAB" toColID="tblCol_1c66350f51e540d1a80bb480f0c2390b" />
    <Link partId="227" fromNodeOrder="0" fromItemID="query_query_YP_PRODUCT_FAB" fromColID="queryCol_27" toItemID="tbl_YP_PRODUCT_FAB" toColID="tblCol_fcee6fa9b2f34e7cb4acb70a7c1db57f" />
    <Link partId="228" fromNodeOrder="0" fromItemID="query_query_YP_PRODUCT_FAB" fromColID="queryCol_28" toItemID="tbl_YP_PRODUCT_FAB" toColID="tblCol_2c1c786f95d14e2993e757e2088f98ca" />
    <Link partId="229" fromNodeOrder="0" fromItemID="query_query_YP_PRODUCT_FAB" fromColID="queryCol_29" toItemID="tbl_YP_PRODUCT_FAB" toColID="tblCol_6c57bb25848d44ffa20eaa88fc0541ef" />
    <Link partId="230" fromNodeOrder="0" fromItemID="query_query_YP_PRODUCT_FAB" fromColID="queryCol_30" toItemID="tbl_YP_PRODUCT_FAB" toColID="tblCol_2a7da9273ee143678371f8b7bb547d74" />
    <Link partId="231" fromNodeOrder="0" fromItemID="query_query_YP_PRODUCT_FAB" fromColID="queryCol_31" toItemID="tbl_YP_PRODUCT_FAB" toColID="tblCol_9d068fca97dd4ee093d93a506f9eef00" />
    <Link partId="232" fromNodeOrder="0" fromItemID="query_query_YP_PRODUCT_FAB" fromColID="queryCol_32" toItemID="tbl_YP_PRODUCT_FAB" toColID="tblCol_cd5137d988554998baae12349972aa77" />
    <Link partId="233" fromNodeOrder="0" fromItemID="query_query_YP_PRODUCT_FAB" fromColID="queryCol_33" toItemID="tbl_YP_PRODUCT_FAB" toColID="tblCol_a48357f4d8da40e9afeb8684feb01c95" />
    <Link partId="234" fromNodeOrder="0" fromItemID="query_query_YP_PRODUCT_FAB" fromColID="queryCol_34" toItemID="tbl_YP_PRODUCT_FAB" toColID="tblCol_e80e0285c998402ebf3eef405fceabf2" />
    <Link partId="235" fromNodeOrder="0" fromItemID="query_query_YP_PRODUCT_FAB" fromColID="queryCol_35" toItemID="tbl_YP_PRODUCT_FAB" toColID="tblCol_293ab25849ca448094e80744a3b3d08d" />
    <Link partId="236" fromNodeOrder="0" fromItemID="query_query_YP_PRODUCT_FAB" fromColID="queryCol_36" toItemID="tbl_YP_PRODUCT_FAB" toColID="tblCol_c2d1748b9ed4442dafac16ebb58b8311" />
    <Link partId="237" fromNodeOrder="0" fromItemID="query_query_YP_PRODUCT_FAB" fromColID="queryCol_37" toItemID="tbl_YP_PRODUCT_FAB" toColID="tblCol_dc248d94c0dd4967b35c74ec05c40b05" />
    <Link partId="238" fromNodeOrder="0" fromItemID="query_query_YP_PRODUCT_FAB" fromColID="queryCol_38" toItemID="tbl_YP_PRODUCT_FAB" toColID="tblCol_a3e6634239a5446bb7880ab19b0cf97c" />
    <Link partId="239" fromNodeOrder="0" fromItemID="query_query_YP_PRODUCT_FAB" fromColID="queryCol_39" toItemID="tbl_YP_PRODUCT_FAB" toColID="tblCol_4952738029ef4e8897d9095a607e3e8e" />
    <Link partId="240" fromNodeOrder="0" fromItemID="query_query_YP_PRODUCT_FAB" fromColID="queryCol_40" toItemID="tbl_YP_PRODUCT_FAB" toColID="tblCol_fb6586b0e63e40d7be2809fbc2af95e5" />
    <Link partId="241" fromNodeOrder="0" fromItemID="query_query_YP_PRODUCT_FAB" fromColID="queryCol_41" toItemID="tbl_YP_PRODUCT_FAB" toColID="tblCol_242395b7061d4ec487f07bc640e188e8" />
    <Link partId="242" fromNodeOrder="0" fromItemID="query_query_YP_PRODUCT_FAB" fromColID="queryCol_42" toItemID="tbl_YP_PRODUCT_FAB" toColID="tblCol_43e7ee987a224dc4bb9af0af3deb29bf" />
    <Link partId="243" fromNodeOrder="0" fromItemID="query_query_YP_PRODUCT_FAB" fromColID="queryCol_43" toItemID="tbl_YP_PRODUCT_FAB" toColID="tblCol_bb1533186e394baf90303ac49a5744d1" />
    <Link partId="244" fromNodeOrder="0" fromItemID="query_query_YP_PRODUCT_FAB" fromColID="queryCol_44" toItemID="tbl_YP_PRODUCT_FAB" toColID="tblCol_6d72661d9137404eb955b77b870411a0" />
    <Link partId="245" fromNodeOrder="0" fromItemID="query_query_YP_PRODUCT_FAB" fromColID="queryCol_45" toItemID="tbl_YP_PRODUCT_FAB" toColID="tblCol_ada1405930254f79b6207ee6c7027220" />
    <Link partId="246" fromNodeOrder="0" fromItemID="query_query_YP_PRODUCT_FAB" fromColID="queryCol_46" toItemID="tbl_YP_PRODUCT_FAB" toColID="tblCol_a2ea44e421d64361acb4e19f52118609" />
    <Link partId="247" fromNodeOrder="0" fromItemID="query_query_YP_PRODUCT_FAB" fromColID="queryCol_47" toItemID="tbl_YP_PRODUCT_FAB" toColID="tblCol_a00a8ef585c54be88de6c61ad29ca672" />
    <Link partId="248" fromNodeOrder="0" fromItemID="query_query_YP_PRODUCT_FAB" fromColID="queryCol_48" toItemID="tbl_YP_PRODUCT_FAB" toColID="tblCol_5cd762b9fba24a00ac62fdb0a9f58bc4" />
    <Link partId="249" fromNodeOrder="0" fromItemID="query_query_YP_PRODUCT_FAB" fromColID="queryCol_49" toItemID="tbl_YP_PRODUCT_FAB" toColID="tblCol_0dfe09168fdf447fbca6f521abc18b60" />
    <Link partId="250" fromNodeOrder="0" fromItemID="query_query_YP_PRODUCT_FAB" fromColID="queryCol_50" toItemID="tbl_YP_PRODUCT_FAB" toColID="tblCol_f1c24eefbc5b49f9bfb1728a2af25593" />
    <Link partId="251" fromNodeOrder="0" fromItemID="query_query_YP_PRODUCT_FAB" fromColID="queryCol_51" toItemID="tbl_YP_PRODUCT_FAB" toColID="tblCol_bb3fa664ca1c49e080eb77fc8b4a74dc" />
    <Link partId="252" fromNodeOrder="0" fromItemID="query_query_YP_PRODUCT_FAB" fromColID="queryCol_52" toItemID="tbl_YP_PRODUCT_FAB" toColID="tblCol_18725aec15e04b6c91ab27caf0875249" />
    <Link partId="253" fromNodeOrder="0" fromItemID="query_query_YP_PRODUCT_FAB" fromColID="queryCol_53" toItemID="tbl_YP_PRODUCT_FAB" toColID="tblCol_a152db93cd5e4a7c9607466a7b3445e3" />
    <Link partId="254" fromNodeOrder="0" fromItemID="query_query_YP_PRODUCT_FAB" fromColID="queryCol_54" toItemID="tbl_YP_PRODUCT_FAB" toColID="tblCol_38083eb65fd64544b088a9d8db951d73" />
    <Link partId="255" fromNodeOrder="0" fromItemID="query_query_YP_PRODUCT_FAB" fromColID="queryCol_55" toItemID="tbl_YP_PRODUCT_FAB" toColID="tblCol_0908d4797fdf4885b8dcf7fa28d3d636" />
    <Link partId="256" fromNodeOrder="0" fromItemID="query_query_YP_PRODUCT_FAB" fromColID="queryCol_56" toItemID="tbl_YP_PRODUCT_FAB" toColID="tblCol_005a8e04b0724055b11267a63781a002" />
    <Link partId="257" fromNodeOrder="0" fromItemID="query_query_YP_PRODUCT_FAB" fromColID="queryCol_57" toItemID="tbl_YP_PRODUCT_FAB" toColID="tblCol_be3aa171e05b445bbd6ec41e859f2858" />
    <Link partId="258" fromNodeOrder="0" fromItemID="query_query_YP_PRODUCT_FAB" fromColID="queryCol_58" toItemID="tbl_YP_PRODUCT_FAB" toColID="tblCol_dd3543f706884b53b4c76db513859160" />
    <Link partId="259" fromNodeOrder="0" fromItemID="query_query_YP_PRODUCT_FAB" fromColID="queryCol_59" toItemID="tbl_YP_PRODUCT_FAB" toColID="tblCol_7bbf959b47ab498680a888b227580f78" />
    <Link partId="260" fromNodeOrder="0" fromItemID="query_query_YP_PRODUCT_FAB" fromColID="queryCol_60" toItemID="tbl_YP_PRODUCT_FAB" toColID="tblCol_a3e0aa37cf064865994bfb12bcbb5433" />
    <Link partId="261" fromNodeOrder="0" fromItemID="query_query_YP_PRODUCT_FAB" fromColID="queryCol_61" toItemID="tbl_YP_PRODUCT_FAB" toColID="tblCol_c23ea2286a0f45c9b5fc3ed282cd0207" />
    <Link partId="262" fromNodeOrder="0" fromItemID="query_query_YP_PRODUCT_FAB" fromColID="queryCol_62" toItemID="tbl_YP_PRODUCT_FAB" toColID="tblCol_110b5ba11e864557b2703fb52786224d" />
    <Link partId="263" fromNodeOrder="0" fromItemID="query_query_YP_PRODUCT_FAB" fromColID="queryCol_63" toItemID="tbl_YP_PRODUCT_FAB" toColID="tblCol_69e127d213924db4bae7a14d44c9437e" />
    <Link partId="264" fromNodeOrder="0" fromItemID="query_query_YP_PRODUCT_FAB" fromColID="queryCol_64" toItemID="tbl_YP_PRODUCT_FAB" toColID="tblCol_8ee0ef07e88f4327b4f22c8cefe44898" />
    <Link partId="265" fromNodeOrder="0" fromItemID="query_query_YP_PRODUCT_FAB" fromColID="queryCol_65" toItemID="tbl_YP_PRODUCT_FAB" toColID="tblCol_e248c76859ae499db5965d006ed0d8ab" />
    <Link partId="266" fromNodeOrder="0" fromItemID="query_query_YP_PRODUCT_FAB" fromColID="queryCol_66" toItemID="tbl_YP_PRODUCT_FAB" toColID="tblCol_8d89bce7c63542518d5235207f436180" />
    <Link partId="267" fromNodeOrder="0" fromItemID="query_query_YP_PRODUCT_FAB" fromColID="queryCol_67" toItemID="tbl_YP_PRODUCT_FAB" toColID="tblCol_e667b2ca706a4b1d9d6e3e6f5134b363" />
    <Link partId="268" fromNodeOrder="0" fromItemID="query_query_YP_PRODUCT_FAB" fromColID="queryCol_68" toItemID="tbl_YP_PRODUCT_FAB" toColID="tblCol_bfc68f39fe4d4ac688eefe8f718b66fc" />
    <Link partId="269" fromNodeOrder="0" fromItemID="query_query_YP_PRODUCT_FAB" fromColID="queryCol_69" toItemID="tbl_YP_PRODUCT_FAB" toColID="tblCol_0fc5ede606084382866e43a1b047638a" />
    <Link partId="270" fromNodeOrder="0" fromItemID="query_query_YP_PRODUCT_FAB" fromColID="queryCol_70" toItemID="tbl_YP_PRODUCT_FAB" toColID="tblCol_a436f1a5c484431b92d03d11de4d94c9" />
    <Link partId="271" fromNodeOrder="0" fromItemID="query_query_YP_PRODUCT_FAB" fromColID="queryCol_71" toItemID="tbl_YP_PRODUCT_FAB" toColID="tblCol_746247adf6a54f43b57bf13f5d01e244" />
    <Link partId="272" fromNodeOrder="0" fromItemID="query_query_YP_PRODUCT_FAB" fromColID="queryCol_72" toItemID="tbl_YP_PRODUCT_FAB" toColID="tblCol_1bbee6f4fb0a4710bcd77423aeec8455" />
    <Link partId="273" fromNodeOrder="0" fromItemID="query_query_YP_PRODUCT_FAB" fromColID="queryCol_73" toItemID="tbl_YP_PRODUCT_FAB" toColID="tblCol_f106b488749e44518785d7378944bf19" />
    <Link partId="274" fromNodeOrder="0" fromItemID="query_query_YP_PRODUCT_FAB" fromColID="queryCol_74" toItemID="tbl_YP_PRODUCT_FAB" toColID="tblCol_1827004b703a43d59738dcceb5747952" />
    <Link partId="275" fromNodeOrder="0" fromItemID="query_query_YP_PRODUCT_FAB" fromColID="queryCol_75" toItemID="tbl_YP_PRODUCT_FAB" toColID="tblCol_65af7836b7ee4e13a8deec6bedac67c2" />
    <Link partId="276" fromNodeOrder="0" fromItemID="query_query_YP_PRODUCT_FAB" fromColID="queryCol_76" toItemID="tbl_YP_PRODUCT_FAB" toColID="tblCol_17b6dc77b30845fa9301f8d91cc90720" />
    <Link partId="277" fromNodeOrder="0" fromItemID="query_query_YP_PRODUCT_FAB" fromColID="queryCol_77" toItemID="tbl_YP_PRODUCT_FAB" toColID="tblCol_cf31ad95ca4d448895dbb7abc5e12b82" />
    <Link partId="278" fromNodeOrder="0" fromItemID="query_query_YP_PRODUCT_FAB" fromColID="queryCol_78" toItemID="tbl_YP_PRODUCT_FAB" toColID="tblCol_f19abb5a4bf4402c9ebd3b8c1222855c" />
    <Link partId="279" fromNodeOrder="0" fromItemID="query_query_YP_PRODUCT_FAB" fromColID="queryCol_79" toItemID="tbl_YP_PRODUCT_FAB" toColID="tblCol_fcbfc068ccc24f008037a4dc6ed201a7" />
    <Link partId="280" fromNodeOrder="0" fromItemID="query_query_YP_PRODUCT_FAB" fromColID="queryCol_80" toItemID="tbl_YP_PRODUCT_FAB" toColID="tblCol_edb6c727dab64a50bf050f491ac59454" />
    <Link partId="281" fromNodeOrder="0" fromItemID="query_query_YP_PRODUCT_FAB" fromColID="queryCol_81" toItemID="tbl_YP_PRODUCT_FAB" toColID="tblCol_5b5d209c89ec4ee699e11380aaadc6bb" />
    <Link partId="282" fromNodeOrder="0" fromItemID="query_query_YP_PRODUCT_FAB" fromColID="queryCol_82" toItemID="tbl_YP_PRODUCT_FAB" toColID="tblCol_b0c713c11aff47b1afea0bb1a3b35d4d" />
    <Link partId="283" fromNodeOrder="0" fromItemID="query_query_YP_PRODUCT_FAB" fromColID="queryCol_83" toItemID="tbl_YP_PRODUCT_FAB" toColID="tblCol_73252b68e7a3485696de7a0e6b851da8" />
    <Link partId="284" fromNodeOrder="0" fromItemID="query_query_YP_PRODUCT_FAB" fromColID="queryCol_84" toItemID="tbl_YP_PRODUCT_FAB" toColID="tblCol_203d907c3e424d85b4d0e3d4d13869d7" />
    <Link partId="285" fromNodeOrder="0" fromItemID="query_query_YP_PRODUCT_FAB" fromColID="queryCol_85" toItemID="tbl_YP_PRODUCT_FAB" toColID="tblCol_c8d7c44382c6458babcf6fc137ddba43" />
    <Link partId="286" fromNodeOrder="0" fromItemID="query_query_YP_PRODUCT_FAB" fromColID="queryCol_86" toItemID="tbl_YP_PRODUCT_FAB" toColID="tblCol_40bfa40fe03646faaffffe42ec24cda6" />
    <Link partId="287" fromNodeOrder="0" fromItemID="query_query_YP_PRODUCT_FAB" fromColID="queryCol_87" toItemID="tbl_YP_PRODUCT_FAB" toColID="tblCol_e9b85d80e2b04bd88b06c3f5fa865032" />
    <Link partId="288" fromNodeOrder="0" fromItemID="query_query_YP_PRODUCT_FAB" fromColID="queryCol_88" toItemID="tbl_YP_PRODUCT_FAB" toColID="tblCol_bd69fc48877a497c83768dd0d6e9284e" />
    <Link partId="289" fromNodeOrder="0" fromItemID="query_query_YP_PRODUCT_FAB" fromColID="queryCol_89" toItemID="tbl_YP_PRODUCT_FAB" toColID="tblCol_d808804d587a4e52b367cb3fe6aa4898" />
    <Link partId="290" fromNodeOrder="0" fromItemID="query_query_YP_PRODUCT_FAB" fromColID="queryCol_90" toItemID="tbl_YP_PRODUCT_FAB" toColID="tblCol_aaf6957dde2a41c1886eb11fc5a24176" />
    <Link partId="291" fromNodeOrder="0" fromItemID="query_query_YP_PRODUCT_FAB" fromColID="queryCol_91" toItemID="tbl_YP_PRODUCT_FAB" toColID="tblCol_6796014994ac4779949689021500b5c7" />
    <Link partId="292" fromNodeOrder="0" fromItemID="query_query_YP_PRODUCT_FAB" fromColID="queryCol_92" toItemID="tbl_YP_PRODUCT_FAB" toColID="tblCol_84233acd1a584105952a9e8de30937db" />
    <Link partId="293" fromNodeOrder="0" fromItemID="query_query_YP_PRODUCT_FAB" fromColID="queryCol_93" toItemID="tbl_YP_PRODUCT_FAB" toColID="tblCol_e8b53a798d7f4031826050df0c506ad0" />
    <Link partId="294" fromNodeOrder="0" fromItemID="query_query_YP_PRODUCT_FAB" fromColID="queryCol_94" toItemID="tbl_YP_PRODUCT_FAB" toColID="tblCol_1ecc404b43904709987a4f8ab4331e6f" />
    <Link partId="295" fromNodeOrder="0" fromItemID="query_query_YP_PRODUCT_FAB" fromColID="queryCol_95" toItemID="tbl_YP_PRODUCT_FAB" toColID="tblCol_ad8616bd59bb4e97a2a13d3bab760c27" />
    <Link partId="296" fromNodeOrder="0" fromItemID="query_query_YP_PRODUCT_FAB" fromColID="queryCol_96" toItemID="tbl_YP_PRODUCT_FAB" toColID="tblCol_100ded5d5a934e47b1633a14bc5117f6" />
    <Link partId="297" fromNodeOrder="0" fromItemID="query_query_YP_PRODUCT_FAB" fromColID="queryCol_97" toItemID="tbl_YP_PRODUCT_FAB" toColID="tblCol_a9ebc3deb7e6490186d3249aa7097b22" />
  </LinksList>
  <ModeKeyColumnIDs />
</TablePopulationObject>